simo_fleet/__init__.py
simo_fleet/admin.py
simo_fleet/api.py
simo_fleet/auto_urls.py
simo_fleet/ble.py
simo_fleet/controllers.py
simo_fleet/forms.py
simo_fleet/gateways.py
simo_fleet/models.py
simo_fleet/routing.py
simo_fleet/serializers.py
simo_fleet/socket_consumers.py
simo_fleet/tasks.py
simo_fleet/utils.py
simo_fleet/views.py
simo_fleet/__pycache__/__init__.cpython-38.pyc
simo_fleet/__pycache__/admin.cpython-38.pyc
simo_fleet/__pycache__/api.cpython-38.pyc
simo_fleet/__pycache__/auto_urls.cpython-38.pyc
simo_fleet/__pycache__/ble.cpython-38.pyc
simo_fleet/__pycache__/controllers.cpython-38.pyc
simo_fleet/__pycache__/forms.cpython-38.pyc
simo_fleet/__pycache__/gateways.cpython-38.pyc
simo_fleet/__pycache__/models.cpython-38.pyc
simo_fleet/__pycache__/routing.cpython-38.pyc
simo_fleet/__pycache__/serializers.cpython-38.pyc
simo_fleet/__pycache__/socket_consumers.cpython-38.pyc
simo_fleet/__pycache__/tasks.cpython-38.pyc
simo_fleet/__pycache__/utils.cpython-38.pyc
simo_fleet/__pycache__/views.cpython-38.pyc
simo_fleet/migrations/0001_initial.py
simo_fleet/migrations/0002_auto_20220422_0743.py
simo_fleet/migrations/0003_auto_20220422_0752.py
simo_fleet/migrations/0004_auto_20220422_0818.py
simo_fleet/migrations/0005_auto_20220428_0900.py
simo_fleet/migrations/0006_rename_mac_colonel_uid.py
simo_fleet/migrations/0007_colonel_socket_connected.py
simo_fleet/migrations/0008_i2cinterface.py
simo_fleet/migrations/0009_i2cinterface_name.py
simo_fleet/migrations/0010_auto_20220602_0746.py
simo_fleet/migrations/0011_i2cinterface_freq.py
simo_fleet/migrations/0012_colonel_logs_stream.py
simo_fleet/migrations/0013_alter_colonel_last_seen.py
simo_fleet/migrations/0014_auto_20220614_0659.py
simo_fleet/migrations/0015_auto_20220614_0754.py
simo_fleet/migrations/0016_auto_20220704_0840.py
simo_fleet/migrations/0017_alter_colonel_secret.py
simo_fleet/migrations/0018_colonel_instance.py
simo_fleet/migrations/0019_auto_20231006_0749.py
simo_fleet/migrations/0020_instanceoptions.py
simo_fleet-1.0.2.dist-info/LICENSE.md
simo_fleet-1.0.2.dist-info/METADATA
simo_fleet-1.0.2.dist-info/WHEEL
simo_fleet-1.0.2.dist-info/top_level.txt
simo_fleet-1.0.2.dist-info/RECORD
