Metadata-Version: 2.1
Name: simo-fleet
Version: 1.0.2
Summary: SIMO.io fleet devices integration
Author-email: Simanas Venčkauskas <simanas@simo.io>
Project-URL: Homepage, https://github.com/SIMO-io/simo-fleet
Project-URL: Issues, https://github.com/SIMO-io/simo-fleet/issues
Classifier: Programming Language :: Python :: 3
Classifier: License :: OSI Approved :: MIT License
Classifier: Operating System :: OS Independent
Requires-Python: >=3.8
License-File: LICENSE.md
Requires-Dist: simo >=1.5.9
